whizoai/__init__.py
whizoai/client.py
whizoai/exceptions.py
whizoai-1.0.0.dist-info/licenses/LICENSE
whizoai-1.0.0.dist-info/METADATA
whizoai-1.0.0.dist-info/WHEEL
whizoai-1.0.0.dist-info/top_level.txt
whizoai-1.0.0.dist-info/RECORD
