Metadata-Version: 2.4
Name: whizoai
Version: 1.0.0
Summary: Official WhizoAI SDK for Python - Enterprise-grade web scraping API client
Author-email: WhizoAI Team <support@whizo.ai>
License: MIT
Project-URL: Homepage, https://whizo.ai
Project-URL: Documentation, https://docs.whizo.ai
Project-URL: Repository, https://github.com/whizoai/whizoai-sdks
Project-URL: Bug Tracker, https://github.com/whizoai/whizoai-sdks/issues
Keywords: whizoai,web-scraping,scraping,crawler,data-extraction,ai-extraction
Classifier: Development Status :: 5 - Production/Stable
Classifier: Intended Audience :: Developers
Classifier: License :: OSI Approved :: MIT License
Classifier: Programming Language :: Python :: 3
Classifier: Programming Language :: Python :: 3.8
Classifier: Programming Language :: Python :: 3.9
Classifier: Programming Language :: Python :: 3.10
Classifier: Programming Language :: Python :: 3.11
Classifier: Programming Language :: Python :: 3.12
Requires-Python: >=3.8
License-File: LICENSE
Requires-Dist: requests>=2.31.0
Requires-Dist: pydantic>=2.0.0
Requires-Dist: typing-extensions>=4.0.0
Provides-Extra: async
Requires-Dist: aiohttp>=3.9.0; extra == "async"
Dynamic: license-file
